sigmoids/__init__.py
sigmoids/__main__.py
sigmoids-0.0.0.dist-info/LICENSE.txt
sigmoids-0.0.0.dist-info/METADATA
sigmoids-0.0.0.dist-info/WHEEL
sigmoids-0.0.0.dist-info/top_level.txt
sigmoids-0.0.0.dist-info/RECORD
